aiogramx/__init__.py
aiogramx/base.py
aiogramx/calendar.py
aiogramx/checkbox.py
aiogramx/keyboard_meta.py
aiogramx/pagination.py
aiogramx/time_selector.py
aiogramx/utils.py
aiogramx-3.1.3.dist-info/licenses/LICENSE
aiogramx-3.1.3.dist-info/METADATA
aiogramx-3.1.3.dist-info/WHEEL
aiogramx-3.1.3.dist-info/top_level.txt
aiogramx-3.1.3.dist-info/RECORD
