Metadata-Version: 2.4
Name: aiogramx
Version: 3.1.3
Summary: Widgets and tools for Aiogram bots
Author-email: Jasur Yusupov <jasuryusupov14@gmail.com>
Maintainer-email: Jasur Yusupov <jasuryusupov14@gmail.com>
License-Expression: MIT
Project-URL: Homepage, https://github.com/jzr-supove/aiogramx
Project-URL: Issues, https://github.com/jzr-supove/aiogramx/issues
Project-URL: Repository, https://github.com/jzr-supove/aiogramx.git
Keywords: aiogram,telegram,bot,widgets,tools
Classifier: Programming Language :: Python :: 3
Classifier: Framework :: AsyncIO
Classifier: Intended Audience :: Developers
Classifier: Topic :: Software Development :: Libraries
Requires-Python: >=3.9
License-File: LICENSE
Requires-Dist: aiogram<4.0.0,>=3.0.0
Requires-Dist: flipcache>=1.2
Dynamic: license-file
